block/__init__.py
block/__version__.py
block/block.py
block_hosts-0.0.3.dist-info/LICENCE.txt
block_hosts-0.0.3.dist-info/METADATA
block_hosts-0.0.3.dist-info/WHEEL
block_hosts-0.0.3.dist-info/entry_points.txt
block_hosts-0.0.3.dist-info/top_level.txt
block_hosts-0.0.3.dist-info/RECORD
