Metadata-Version: 2.1
Name: block_hosts
Version: 0.0.3
Summary: Block helps you stop procrastinating, since you can't do it by yourself. It is a simple command-line utility that relies on modifying the hosts file to block websites that you use when procrastinating.
Home-page: https://github.com/bbatalo/block
Author: Bojan Batalo
Author-email: bbatalo@hotmail.com
License: MIT
Platform: UNKNOWN
Classifier: License :: OSI Approved :: MIT License
Classifier: Programming Language :: Python
Classifier: Programming Language :: Python :: 3
Classifier: Programming Language :: Python :: 3.6
Classifier: Programming Language :: Python :: 3.7
Classifier: Programming Language :: Python :: Implementation :: CPython
Classifier: Programming Language :: Python :: Implementation :: PyPy
Requires-Python: >=3.6.0
